{"tag":{"label":"mvp","permalink":"/reference/tags/mvp","allTagsPath":"/reference/tags","count":2,"items":[{"id":"mvp_scope","title":"Perimetre MVP et architecture cible","description":"Cadrage fonctionnel et technique du projet Evenements, de P1 a P4.","permalink":"/reference/mvp-scope"},{"id":"sprints/sprint_1_mvp_event_publication_registration","title":"Sprint 1 - MVP publication & inscription","description":"Premier vertical slice backend pour auth, drafts, publication et registration.","permalink":"/reference/sprints/sprint-1-mvp"}],"unlisted":false}}